MANIFEST.in
README.txt
setup.cfg
setup.py
DVDev.egg-info/PKG-INFO
DVDev.egg-info/SOURCES.txt
DVDev.egg-info/dependency_links.txt
DVDev.egg-info/entry_points.txt
DVDev.egg-info/not-zip-safe
DVDev.egg-info/paster_plugins.txt
DVDev.egg-info/requires.txt
DVDev.egg-info/top_level.txt
dvdev/__init__.py
dvdev/commands.py
dvdev/websetup.py
dvdev/config/__init__.py
dvdev/config/deployment.ini_tmpl
dvdev/config/environment.py
dvdev/config/middleware.py
dvdev/config/routing.py
dvdev/controllers/__init__.py
dvdev/controllers/dashboard.py
dvdev/controllers/dv.py
dvdev/controllers/error.py
dvdev/controllers/issues.py
dvdev/controllers/mercurialgateway.py
dvdev/controllers/openiduser.py
dvdev/controllers/wiki.py
dvdev/lib/__init__.py
dvdev/lib/app_globals.py
dvdev/lib/base.py
dvdev/lib/forms.py
dvdev/lib/helpers.py
dvdev/model/__init__.py
dvdev/public/.DS_Store
dvdev/public/bg.png
dvdev/public/favicon.ico
dvdev/public/folder.png
dvdev/public/indexcard.png
dvdev/public/preview.png
dvdev/public/pylons-logo.gif
dvdev/public/resizecorner.png
dvdev/public/css/dvdev.css
dvdev/public/css/cupertino/jquery-ui-1.7.custom.css
dvdev/public/css/cupertino/images/ui-bg_diagonals-small_0_aaaaaa_40x40.png
dvdev/public/css/cupertino/images/ui-bg_diagonals-thick_15_444444_40x40.png
dvdev/public/css/cupertino/images/ui-bg_glass_100_f0f0f0_1x400.png
dvdev/public/css/cupertino/images/ui-bg_glass_50_99c2ff_1x400.png
dvdev/public/css/cupertino/images/ui-bg_glass_55_fbf5d0_1x400.png
dvdev/public/css/cupertino/images/ui-bg_glass_80_e6e6e6_1x400.png
dvdev/public/css/cupertino/images/ui-bg_glass_95_fef1ec_1x400.png
dvdev/public/css/cupertino/images/ui-bg_highlight-hard_100_f9f9f9_1x100.png
dvdev/public/css/cupertino/images/ui-bg_highlight-soft_100_e7eef3_1x100.png
dvdev/public/css/cupertino/images/ui-icons_222222_256x240.png
dvdev/public/css/cupertino/images/ui-icons_2694e8_256x240.png
dvdev/public/css/cupertino/images/ui-icons_2e83ff_256x240.png
dvdev/public/css/cupertino/images/ui-icons_72a7cf_256x240.png
dvdev/public/css/cupertino/images/ui-icons_888888_256x240.png
dvdev/public/css/cupertino/images/ui-icons_cd0a0a_256x240.png
dvdev/public/css/cupertino/images/ui-icons_ffffff_256x240.png
dvdev/public/js/.DS_Store
