Metadata-Version: 1.0
Name: DVDev
Version: 0.1.3
Summary: DVDev - Distributed Development - tools for Open Source Software
Home-page: http://dvdev.org
Author: Douglas Mayle
Author-email: douglas@mayle.org
License: GNU Affero General Public License v3
Platform: UNKNOWN
Classifier: Development Status :: 4 - Beta
Classifier: Environment :: Web Environment
Classifier: Framework :: Pylons
Classifier: Intended Audience :: Developers
Classifier: License :: OSI Approved :: GNU Affero General Public License v3
Classifier: Operating System :: OS Independent
Classifier: Programming Language :: Python :: 2.5
Classifier: Topic :: Internet :: WWW/HTTP :: WSGI :: Application
Classifier: Topic :: Software Development :: Bug Tracking
Classifier: Topic :: Software Development :: Documentation
Classifier: Topic :: Software Development :: Version Control
